caravan/__init__.py
caravan/caravan.cpython-311-darwin.so
caravan_client-0.0.12.dist-info/METADATA
caravan_client-0.0.12.dist-info/WHEEL
caravan_client-0.0.12.dist-info/RECORD
