Metadata-Version: 2.4
Name: caravan-client
Version: 0.0.12
Classifier: Programming Language :: Rust
Classifier: Programming Language :: Python :: Implementation :: CPython
Classifier: Programming Language :: Python :: Implementation :: PyPy
Classifier: License :: OSI Approved :: MIT License
Classifier: Operating System :: OS Independent
Requires-Dist: typeguard>=4.4.0
Requires-Dist: torch==2.7.1
Requires-Dist: numpy>=1.24.4
Requires-Dist: caravanrtorch
Requires-Dist: jedi>=0.19.2
Requires-Dist: torchvision>=0.20.1
Requires-Dist: maturin>=1.9.1
Requires-Dist: dotenv>=0.9.9
Requires-Dist: tqdm>=4.67.1
Summary: A python module used for clients to interface with Caravan.
Author-email: Sourish Saswade <saswade@thecaravan.cloud>, Tejas Prabhune <prabhune@thecaravan.cloud>
Requires-Python: >=3.10
Project-URL: Homepage, https://github.com/tejasprabhune/thava
